{
  "project": "WorkflowAcceptance",
  "source": {
    "implementation_plan_path": "IMPLEMENTATION_PLAN.md",
    "contract_path": "CONTRACT.md"
  },
  "rules": {
    "one_story_per_iteration": true,
    "one_commit_per_story": true,
    "no_prd_rewrite": true,
    "passes_only_flips_after_verify_green": true
  },
  "items": [
    {
      "id": "S1-014",
      "priority": 1,
      "phase": 1,
      "slice": 1,
      "slice_ref": "Slice 1",
      "story_ref": "Story 1",
      "category": "acceptance",
      "description": "Acceptance test story",
      "contract_refs": ["CONTRACT.md ยง1"],
      "plan_refs": ["IMPLEMENTATION_PLAN.md ยง1"],
      "scope": {
        "touch": ["crates/soldier_core/src/lib.rs"],
        "avoid": []
      },
      "acceptance": ["a", "b", "c"],
      "steps": ["1", "2", "3", "4", "5"],
      "verify": ["./plans/verify.sh", "bash -n plans/verify.sh"],
      "evidence": ["log"],
      "contract_must_evidence": [],
      "enforcing_contract_ats": [],
      "reason_codes": { "type": "", "values": [] },
      "enforcement_point": "",
      "failure_mode": [],
      "observability": { "metrics": [], "status_fields": [], "status_contract_ats": [] },
      "implementation_tests": [],
      "dependencies": [],
      "est_size": "S",
      "risk": "low",
      "needs_human_decision": false,
      "passes": false
    }
  ]
}
